README.txt
setup.cfg
setup.py
docs/HISTORY.txt
docs/INSTALL.txt
docs/LICENSE.GPL
docs/LICENSE.txt
icsemantic/__init__.py
icsemantic.thesaurus.egg-info/PKG-INFO
icsemantic.thesaurus.egg-info/SOURCES.txt
icsemantic.thesaurus.egg-info/dependency_links.txt
icsemantic.thesaurus.egg-info/entry_points.txt
icsemantic.thesaurus.egg-info/namespace_packages.txt
icsemantic.thesaurus.egg-info/not-zip-safe
icsemantic.thesaurus.egg-info/requires.txt
icsemantic.thesaurus.egg-info/top_level.txt
icsemantic/thesaurus/README.txt
icsemantic/thesaurus/TODO.txt
icsemantic/thesaurus/Thesaurus.py
icsemantic/thesaurus/__init__.py
icsemantic/thesaurus/browser.txt
icsemantic/thesaurus/config.py
icsemantic/thesaurus/configure.zcml
icsemantic/thesaurus/interfaces.py
icsemantic/thesaurus/patches.py
icsemantic/thesaurus/preferences.py
icsemantic/thesaurus/refresh.txt
icsemantic/thesaurus/revision.txt
icsemantic/thesaurus/version.txt
icsemantic/thesaurus/vocabularies.py
icsemantic/thesaurus/vocabularies.zcml
icsemantic/thesaurus/Extensions/__init__.py
icsemantic/thesaurus/Extensions/install.py
icsemantic/thesaurus/browser/__init__.py
icsemantic/thesaurus/browser/admin.py
icsemantic/thesaurus/browser/admin.zcml
icsemantic/thesaurus/browser/autocomplete.py
icsemantic/thesaurus/browser/azaxview.py
icsemantic/thesaurus/browser/configure.zcml
icsemantic/thesaurus/browser/incrementalSearchSelectWidget.py
icsemantic/thesaurus/browser/incrementalSearchSelectWidget.zcml
icsemantic/thesaurus/browser/templates/autocomplete.kss
icsemantic/thesaurus/browser/templates/dragAndDrop.css
icsemantic/thesaurus/browser/templates/dragAndDrop.js
icsemantic/thesaurus/browser/templates/dragAndDrop.kss
icsemantic/thesaurus/browser/templates/incrementalSearchSelect-widget.pt
icsemantic/thesaurus/browser/templates/thesaurus-autocomplete.pt
icsemantic/thesaurus/browser/templates/thesaurus-download.pt
icsemantic/thesaurus/browser/templates/thesaurus-query.pt
icsemantic/thesaurus/skins/icsemantic.thesaurus/__init__.py
icsemantic/thesaurus/skins/icsemantic.thesaurus/incrementalSearchSelectWidget.css
icsemantic/thesaurus/skins/icsemantic.thesaurus/incrementalSearchSelectWidget.kss
icsemantic/thesaurus/tests/__init__.py
icsemantic/thesaurus/tests/base.py
icsemantic/thesaurus/tests/test_addtranslation_patch.py
icsemantic/thesaurus/tests/test_addtranslation_patch.txt
