Metadata-Version: 1.0
Name: icsemantic.thesaurus
Version: 1.0-dev-r371
Summary: icSemantic.Thesaurus
Home-page: http://www.platecom.com/productos/icsemantic.thesaurus/
Author: Inter-Cultura Consultora SRL - Ibai Sistemas SA - Eusko Ikaskuntza-Sociedad de Estudios Vascos
Author-email: dev@inter-cultura.com
License: GPL
Keywords: icsemantic,platecom,semantic,thesaurus,owl,rdf,skos,core,queries
Platform: UNKNOWN
Classifier: Topic :: Text Processing :: Indexing
Classifier: Environment :: Web Environment
Classifier: Framework :: Plone
Classifier: Development Status :: 4 - Beta
Classifier: Intended Audience :: Information Technology
Classifier: License :: OSI Approved :: GNU General Public License (GPL)
Classifier: Operating System :: OS Independent
Classifier: Programming Language :: Python
